pyxdist.cp37-win_amd64.pyd
lshashing/__init__.py
lshashing/hash_table.py
lshashing/hash_util.py
lshashing/lsh_random.py
lshashing/para_util.py
lshashing/pq.py
lshashing/util.py
lshashing-1.1.3.dist-info/LICENSE
lshashing-1.1.3.dist-info/METADATA
lshashing-1.1.3.dist-info/WHEEL
lshashing-1.1.3.dist-info/top_level.txt
lshashing-1.1.3.dist-info/RECORD
