Metadata-Version: 2.1
Name: lshashing
Version: 1.1.3
Summary: Nearest neighbors search using locality-sensitive hashing
Home-page: https://github.com/MNoorFawi/lshashing
Author: Muhammad N. Fawi
Author-email: m.noor.fawi@gmail.com
License: MIT
Platform: UNKNOWN
Classifier: License :: OSI Approved :: MIT License
Classifier: Programming Language :: Python :: 3
Classifier: Programming Language :: Python :: 3.7
Requires-Dist: numpy
Requires-Dist: joblib
Requires-Dist: cython
